code/__init__.py
code/local.py
code/models.py
code/utils.py
LSpackage-1.0.dist-info/LICENSE.txt
LSpackage-1.0.dist-info/METADATA
LSpackage-1.0.dist-info/WHEEL
LSpackage-1.0.dist-info/top_level.txt
LSpackage-1.0.dist-info/RECORD
