Metadata-Version: 2.1
Name: LSpackage
Version: 1.0
Summary: An implementation of Local Search algorithms based on single solution design
Home-page: http://github.com/alexandur/LSpackage
Author: Andurnache Alexandru
Author-email: alex.andur@yahoo.com
License: LICENSE.txt
Platform: UNKNOWN
Classifier: Intended Audience :: Developers
Classifier: License :: OSI Approved :: MIT License
Classifier: Natural Language :: English
Classifier: Operating System :: OS Independent
Classifier: Programming Language :: Python
Classifier: Programming Language :: Python :: 3
